highlander_script/H2O_module.py
highlander_script/RFE_module.py
highlander_script/__init__.py
HighlanderML-1.0.1.1.8.dist-info/LICENSE
HighlanderML-1.0.1.1.8.dist-info/METADATA
HighlanderML-1.0.1.1.8.dist-info/WHEEL
HighlanderML-1.0.1.1.8.dist-info/top_level.txt
HighlanderML-1.0.1.1.8.dist-info/RECORD
