Metadata-Version: 2.1
Name: HighlanderML
Version: 1.0.1.1.8
Summary: Highlander project
Author: Pixpit (Giovanni Vignali)
Author-email: <giovanni.vignali@outlook.it>
Keywords: python,machine learning,Weather forecasting,Milk,Climat change
Classifier: Development Status :: 1 - Planning
Classifier: Intended Audience :: Developers
Classifier: Programming Language :: Python :: 3
Classifier: Operating System :: Unix
Classifier: Operating System :: MacOS :: MacOS X
Classifier: Operating System :: Microsoft :: Windows
License-File: LICENSE
Requires-Dist: pandas (>=1.3.4)
Requires-Dist: numpy (>=1.21.2)
Requires-Dist: scikit-learn (>=1.0)
Requires-Dist: h2o (>=3.38.0.1)
